yaml_cli/__init__.py
yaml_cli/version.py
yaml_cli-0.0.8.dist-info/LICENSE.txt
yaml_cli-0.0.8.dist-info/METADATA
yaml_cli-0.0.8.dist-info/WHEEL
yaml_cli-0.0.8.dist-info/entry_points.txt
yaml_cli-0.0.8.dist-info/top_level.txt
yaml_cli-0.0.8.dist-info/RECORD
